flask_minio/__init__.py
flask_minio/extension.py
flask_minio/tests/__init__.py
flask_minio/tests/test_extension.py
flask_minio_factory-0.1.2.dist-info/LICENSE.txt
flask_minio_factory-0.1.2.dist-info/METADATA
flask_minio_factory-0.1.2.dist-info/WHEEL
flask_minio_factory-0.1.2.dist-info/top_level.txt
flask_minio_factory-0.1.2.dist-info/RECORD
